isolated_logging/__init__.py
isolated_logging/functional.py
isolated_logging/py.typed
isolated_logging-0.1.2.dist-info/licenses/LICENSE
isolated_logging-0.1.2.dist-info/METADATA
isolated_logging-0.1.2.dist-info/WHEEL
isolated_logging-0.1.2.dist-info/top_level.txt
isolated_logging-0.1.2.dist-info/RECORD
