Metadata-Version: 2.4
Name: isolated-logging
Version: 0.1.2
Summary: A Python library for tracking and logging function and loop execution times with stats and color-coded logs for easy performance monitoring and optimization.
Author-email: Juan Urrutia <juan.urrutia.gandolfo@gmail.com>
Project-URL: Homepage, https://github.com/jurrutiag/isolated-logging
Project-URL: Repository, https://github.com/jurrutiag/isolated-logging
Classifier: Operating System :: Unix
Classifier: Operating System :: POSIX
Classifier: Operating System :: Microsoft :: Windows
Classifier: Programming Language :: Python
Classifier: Programming Language :: Python :: 3.10
Classifier: Programming Language :: Python :: 3.11
Classifier: Programming Language :: Python :: 3.12
Requires-Python: >=3.10
License-File: LICENSE
Requires-Dist: numpy
Requires-Dist: loky
Provides-Extra: testing
Requires-Dist: pytest>=6.0; extra == "testing"
Requires-Dist: pytest-cov>=2.0; extra == "testing"
Dynamic: license-file
